amp_C.cpython-39-x86_64-linux-gnu.so
apex_C.cpython-39-x86_64-linux-gnu.so
distributed_adam_cuda.cpython-39-x86_64-linux-gnu.so
fused_adam_cuda.cpython-39-x86_64-linux-gnu.so
fused_dense_cuda.cpython-39-x86_64-linux-gnu.so
fused_layer_norm_cuda.cpython-39-x86_64-linux-gnu.so
fused_weight_gradient_mlp_cuda.cpython-39-x86_64-linux-gnu.so
generic_scaled_masked_softmax_cuda.cpython-39-x86_64-linux-gnu.so
mlp_cuda.cpython-39-x86_64-linux-gnu.so
scaled_masked_softmax_cuda.cpython-39-x86_64-linux-gnu.so
scaled_softmax_cuda.cpython-39-x86_64-linux-gnu.so
scaled_upper_triang_masked_softmax_cuda.cpython-39-x86_64-linux-gnu.so
syncbn.cpython-39-x86_64-linux-gnu.so
apex/__init__.py
apex/_autocast_utils.py
apex/RNN/RNNBackend.py
apex/RNN/__init__.py
apex/RNN/cells.py
apex/RNN/models.py
apex/amp/__init__.py
apex/amp/__version__.py
apex/amp/_amp_state.py
apex/amp/_initialize.py
apex/amp/_process_optimizer.py
apex/amp/amp.py
apex/amp/compat.py
apex/amp/frontend.py
apex/amp/handle.py
apex/amp/opt.py
apex/amp/rnn_compat.py
apex/amp/scaler.py
apex/amp/utils.py
apex/amp/wrap.py
apex/amp/lists/__init__.py
apex/amp/lists/functional_overrides.py
apex/amp/lists/tensor_overrides.py
apex/amp/lists/torch_overrides.py
apex/contrib/__init__.py
apex/contrib/bottleneck/__init__.py
apex/contrib/bottleneck/bottleneck.py
apex/contrib/bottleneck/halo_exchangers.py
apex/contrib/bottleneck/test.py
apex/contrib/clip_grad/__init__.py
apex/contrib/clip_grad/clip_grad.py
apex/contrib/conv_bias_relu/__init__.py
apex/contrib/conv_bias_relu/conv_bias_relu.py
apex/contrib/cudnn_gbn/__init__.py
apex/contrib/cudnn_gbn/batch_norm.py
apex/contrib/fmha/__init__.py
apex/contrib/fmha/fmha.py
apex/contrib/focal_loss/__init__.py
apex/contrib/focal_loss/focal_loss.py
apex/contrib/group_norm/__init__.py
apex/contrib/group_norm/group_norm.py
apex/contrib/groupbn/__init__.py
apex/contrib/groupbn/batch_norm.py
apex/contrib/index_mul_2d/__init__.py
apex/contrib/index_mul_2d/index_mul_2d.py
apex_personal-0.1.dist-info/LICENSE
apex_personal-0.1.dist-info/METADATA
apex_personal-0.1.dist-info/WHEEL
apex_personal-0.1.dist-info/top_level.txt
apex_personal-0.1.dist-info/RECORD
