Metadata-Version: 2.1
Name: apex-personal
Version: 0.1
Summary: PyTorch Extensions written by NVIDIA
License-File: LICENSE
Requires-Dist: packaging >20.6
